_pmmc.cpython-38-x86_64-linux-gnu.so
pmmc/__init__.py
pmmc.libs/libOpenCL-f806d0e1.so.1.0.0
pmmc.libs/libgomp-a34b3233.so.1.0.0
pmmc-0.3.7.dist-info/METADATA
pmmc-0.3.7.dist-info/WHEEL
pmmc-0.3.7.dist-info/top_level.txt
pmmc-0.3.7.dist-info/RECORD
pmmc-0.3.7.dist-info/sboms/auditwheel.cdx.json
