Metadata-Version: 2.4
Name: pmmc
Version: 0.3.7
Summary: Python bindings for Mesh-based Monte Carlo (MMC) photon transport simulator
Home-page: https://github.com/fangq/mmc
Download-URL: https://mcx.space
Author: Qianqian Fang
Author-email: q.fang@neu.edu
Maintainer: Qianqian Fang
License: GPLv3+
Keywords: Monte Carlo simulation,Biophotonics,Ray-tracing,Rendering,GPU,Modeling,Biomedical Optics,Tissue Optics,Simulator,Optics,OpenCL
Classifier: Development Status :: 4 - Beta
Classifier: Intended Audience :: Science/Research
Classifier: Environment :: GPU
Classifier: Topic :: Scientific/Engineering :: Physics
Classifier: License :: OSI Approved :: GNU General Public License v3 or later (GPLv3+)
Classifier: Programming Language :: Python :: 3.6
Classifier: Programming Language :: Python :: 3.7
Classifier: Programming Language :: Python :: 3.8
Classifier: Programming Language :: Python :: 3.9
Classifier: Programming Language :: Python :: 3.10
Classifier: Programming Language :: Python :: 3.11
Classifier: Programming Language :: Python :: 3.12
Classifier: Programming Language :: Python :: 3.13
Requires: numpy
Requires-Python: >=3.6
Dynamic: author
Dynamic: author-email
Dynamic: classifier
Dynamic: description
Dynamic: description-content-type
Dynamic: download-url
Dynamic: home-page
Dynamic: keywords
Dynamic: license
Dynamic: maintainer
Dynamic: requires
Dynamic: requires-python
Dynamic: summary
